gm1_resource_viewer/__init__.py
gm1_resource_viewer/color_converter.py
gm1_resource_viewer/color_table.py
gm1_resource_viewer/gm1_reader.py
gm1_resource_viewer/palette.py
gm1_resource_viewer/tgx_image.py
gm1_resource_viewer/tile_image.py
gm1_resource_viewer/utility.py
gm_resource_modifier-0.1.0.dist-info/LICENSE
gm_resource_modifier-0.1.0.dist-info/LICENSE-original
gm_resource_modifier-0.1.0.dist-info/METADATA
gm_resource_modifier-0.1.0.dist-info/WHEEL
gm_resource_modifier-0.1.0.dist-info/RECORD
